{
  "type": "FeatureCollection",
  "features": [
    {
      "type": "Feature",
      "properties": {},
      "geometry": {
        "type": "Point",
        "coordinates": [
          66.610107421875,
          28.265682390146477
        ]
      }
    },
    {
      "type": "Feature",
      "properties": {},
      "geometry": {
        "type": "Polygon",
        "coordinates": [
          [
            [
              74.37787860631943,
              32.91607555212818
            ],
            [
              74.37816560268402,
              32.915890918512204
            ],
            [
              74.37837213277817,
              32.91562072228241
            ],
            [
              74.37844187021255,
              32.91519741319741
            ],
            [
              74.37831312417984,
              32.91472231388775
            ],
            [
              74.3779993057251,
              32.9144138357194
            ],
            [
              74.37774181365967,
              32.91442959740371
            ],
            [
              74.37703371047974,
              32.91479436702765
            ],
            [
              74.37658041715622,
              32.91517939999995
            ],
            [
              74.37635779380798,
              32.91531224724505
            ],
            [
              74.37621027231216,
              32.9154023130605
            ],
            [
              74.37615126371384,
              32.915438339361025
            ],
            [
              74.37557458877563,
              32.91557568949726
            ],
            [
              74.37475383281708,
              32.915514895200964
            ],
            [
              74.37414228916168,
              32.915391054838594
            ],
            [
              74.37377750873566,
              32.91515463184748
            ],
            [
              74.37356293201445,
              32.9150825790008
            ],
            [
              74.37327325344086,
              32.91511635377998
            ],
            [
              74.3730479478836,
              32.915147876895574
            ],
            [
              74.37280386686325,
              32.91517264504996
            ],
            [
              74.37252759933472,
              32.91505781082123
            ],
            [
              74.37227278947829,
              32.91474708216121
            ],
            [
              74.37237471342085,
              32.91446787576817
            ],
            [
              74.37251150608063,
              32.91434403394091
            ],
            [
              74.37294334173203,
              32.913945487248114
            ],
            [
              74.37324911355972,
              32.91388018846635
            ],
            [
              74.37383115291595,
              32.91373382895292
            ],
            [
              74.37443733215332,
              32.91328123877249
            ],
            [
              74.37554508447647,
              32.91335329308546
            ],
            [
              74.37606006860732,
              32.91255618898403
            ],
            [
              74.37658041715622,
              32.91259221644291
            ],
            [
              74.37733680009842,
              32.91295474193193
            ],
            [
              74.37801539897919,
              32.912774605228556
            ],
            [
              74.37864571809769,
              32.912058558208116
            ],
            [
              74.3795308470726,
              32.911774839862055
            ],
            [
              74.37988758087157,
              32.911522645013314
            ],
            [
              74.38072979450226,
              32.911455092699676
            ],
            [
              74.38169002532959,
              32.91138979208085
            ],
            [
              74.38291311264038,
              32.91129972218273
            ],
            [
              74.3836373090744,
              32.91124568019986
            ],
            [
              74.3843212723732,
              32.91120289694004
            ],
            [
              74.38442587852478,
              32.911191638184015
            ],
            [
              74.38499718904495,
              32.91110381983789
            ],
            [
              74.38540756702422,
              32.911038518959955
            ],
            [
              74.38578844070435,
              32.91098672857424
            ],
            [
              74.38607811927795,
              32.9109326864003
            ],
            [
              74.38673257827759,
              32.910833608995766
            ],
            [
              74.38728779554367,
              32.910750293819746
            ],
            [
              74.3875801563263,
              32.91069850326543
            ],
            [
              74.3877625465393,
              32.910678237388076
            ],
            [
              74.38793957233429,
              32.91064671268078
            ],
            [
              74.38822656869887,
              32.91061068443011
            ],
            [
              74.38876032829285,
              32.91052061373933
            ],
            [
              74.38912510871887,
              32.910462067741165
            ],
            [
              74.38946306705475,
              32.910412528789394
            ],
            [
              74.38971787691115,
              32.910369745126935
            ],
            [
              74.39024895429611,
              32.91028868128871
            ],
            [
              74.39054936170578,
              32.91025040111711
            ],
            [
              74.39062714576721,
              32.910234638688685
            ],
            [
              74.39071297645569,
              32.9102301351372
            ],
            [
              74.39079344272614,
              32.9102301351372
            ],
            [
              74.39088463783264,
              32.910239142239945
            ],
            [
              74.39093828201294,
              32.91025040111711
            ],
            [
              74.3909865617752,
              32.91026616354272
            ],
            [
              74.39106702804564,
              32.91029543661142
            ],
            [
              74.39117163419724,
              32.91031795434998
            ],
            [
              74.39128160476685,
              32.91033371676355
            ],
            [
              74.3912923336029,
              32.9103382203098
            ],
            [
              74.39145863056183,
              32.91028192596553
            ],
            [
              74.39177513122559,
              32.9103900110749
            ],
            [
              74.39187973737717,
              32.91041703233162
            ],
            [
              74.39204603433609,
              32.910381003987496
            ],
            [
              74.39218819141388,
              32.9103382203098
            ],
            [
              74.39236253499985,
              32.910259408217804
            ],
            [
              74.39245104789734,
              32.910176092501395
            ],
            [
              74.39243763685225,
              32.91009728026508
            ],
            [
              74.3923571705818,
              32.91001621617739
            ],
            [
              74.39231961965561,
              32.90991938953093
            ],
            [
              74.39236789941788,
              32.90976626810639
            ],
            [
              74.39257711172102,
              32.90955910340464
            ],
            [
              74.39263612031937,
              32.90927087344795
            ],
            [
              74.39268171787262,
              32.90910649188061
            ],
            [
              74.39281314611435,
              32.90906370758698
            ],
            [
              74.39299553632736,
              32.90906370758698
            ],
            [
              74.3930920958519,
              32.90890157744461
            ],
            [
              74.39315915107727,
              32.908757461513254
            ],
            [
              74.39336568117142,
              32.90866288530581
            ],
            [
              74.39358830451965,
              32.90865838167437
            ],
            [
              74.39365267753601,
              32.90863811533004
            ],
            [
              74.39371705055237,
              32.90859758262743
            ],
            [
              74.3937599658966,
              32.908570560815384
            ],
            [
              74.3937948346138,
              32.908498502609625
            ],
            [
              74.39382165670395,
              32.9084827398693
            ],
            [
              74.39389944076538,
              32.90848724350966
            ],
            [
              74.39394235610962,
              32.908521020805225
            ],
            [
              74.39399600028992,
              32.90855704990627
            ],
            [
              74.39414888620375,
              32.90855029445095
            ],
            [
              74.39425885677338,
              32.90848724350966
            ],
            [
              74.3945726752281,
              32.90809542593959
            ],
            [
              74.3945860862732,
              32.90787924998625
            ],
            [
              74.39463436603546,
              32.90767658455064
            ],
            [
              74.39463704824448,
              32.90756849612863
            ],
            [
              74.3945163488388,
              32.90735682258664
            ],
            [
              74.39457803964615,
              32.90722621525509
            ],
            [
              74.39477115869522,
              32.907124881847885
            ],
            [
              74.39477920532227,
              32.907030303896526
            ],
            [
              74.39474701881409,
              32.906974007448945
            ],
            [
              74.39473628997803,
              32.9069199628256
            ],
            [
              74.3947523832321,
              32.90687942933642
            ],
            [
              74.39479529857635,
              32.90680286602849
            ],
            [
              74.39482748508453,
              32.906762332485734
            ],
            [
              74.3948569893837,
              32.906645235480156
            ],
            [
              74.39489185810089,
              32.906501115876104
            ],
            [
              74.39505547285079,
              32.9063907741457
            ],
            [
              74.3951466679573,
              32.90637951477773
            ],
            [
              74.3954175710678,
              32.906402033512244
            ],
            [
              74.39553022384644,
              32.90636825540832
            ],
            [
              74.3956133723259,
              32.906260165389156
            ],
            [
              74.39564019441603,
              32.906235394741174
            ],
            [
              74.39567238092422,
              32.90612955643992
            ],
            [
              74.39559191465378,
              32.905985435996534
            ],
            [
              74.39554363489151,
              32.90590887191557
            ],
            [
              74.39552754163742,
              32.90574898788595
            ],
            [
              74.39559727907181,
              32.905562080837434
            ],
            [
              74.39578503370285,
              32.905388684789045
            ],
            [
              74.39594596624374,
              32.90511620459841
            ],
            [
              74.39624100923538,
              32.904911280927394
            ],
            [
              74.39630270004272,
              32.90476715850112
            ],
            [
              74.39631879329681,
              32.90463204351341
            ],
            [
              74.39637780189514,
              32.904566737862126
            ],
            [
              74.39653068780899,
              32.90453971481992
            ],
            [
              74.39694374799728,
              32.904505936005556
            ],
            [
              74.39706712961197,
              32.904445134107256
            ],
            [
              74.39715027809142,
              32.90436856869443
            ],
            [
              74.39720660448074,
              32.90433704174049
            ],
            [
              74.39731389284134,
              32.90431452248084
            ],
            [
              74.39742654561996,
              32.904350553293554
            ],
            [
              74.39755260944365,
              32.904436126415064
            ],
            [
              74.39770549535751,
              32.904478912944796
            ],
            [
              74.3978664278984,
              32.904445134107256
            ],
            [
              74.39791202545166,
              32.904382080242684
            ],
            [
              74.39787715673447,
              32.90423120117021
            ],
            [
              74.39796298742294,
              32.90411860467997
            ],
            [
              74.39829558134079,
              32.90393394612601
            ],
            [
              74.39846187829971,
              32.90387539577242
            ],
            [
              74.39850211143494,
              32.90387314383495
            ],
            [
              74.3985503911972,
              32.90384612058109
            ],
            [
              74.3985852599144,
              32.90377631047041
            ],
            [
              74.39856916666031,
              32.903395731802505
            ],
            [
              74.39860135316847,
              32.90330790572379
            ],
            [
              74.39872205257414,
              32.90325160690954
            ],
            [
              74.39876765012741,
              32.903213323695425
            ],
            [
              74.39878910779953,
              32.90311423765264
            ],
            [
              74.3988373875618,
              32.902925073081235
            ],
            [
              74.3988561630249,
              32.902907057386706
            ],
            [
              74.39893931150436,
              32.90286201813431
            ],
            [
              74.39900904893875,
              32.902828238679994
            ],
            [
              74.39931213855743,
              32.90277475451761
            ],
            [
              74.39937382936478,
              32.902762931698426
            ],
            [
              74.39950861036777,
              32.90268805380685
            ],
            [
              74.39958103001118,
              32.90253773484092
            ],
            [
              74.39964406192303,
              32.90211830416725
            ],
            [
              74.39971044659615,
              32.90203779577043
            ],
            [
              74.40004907548428,
              32.901875652763074
            ],
            [
              74.40030723810196,
              32.901752356319214
            ],
            [
              74.40073169767857,
              32.90156994482714
            ],
            [
              74.40090402960777,
              32.901608228751684
            ],
            [
              74.40092146396637,
              32.901612169742975
            ],
            [
              74.40110720694065,
              32.90161329574045
            ],
            [
              74.40134659409523,
              32.90166115062012
            ],
            [
              74.40139688551426,
              32.90166959559622
            ],
            [
              74.4015584886074,
              32.90173039940023
            ],
            [
              74.40163291990756,
              32.901735466382014
            ],
            [
              74.40174154937267,
              32.90169436752141
            ],
            [
              74.40180726349354,
              32.90157107082514
            ],
            [
              74.4021774083376,
              32.901375146954685
            ],
            [
              74.40236382186413,
              32.901352626941794
            ],
            [
              74.40253347158432,
              32.90143707696059
            ],
            [
              74.40274201333523,
              32.901461848950824
            ],
            [
              74.40287478268147,
              32.90144608495784
            ],
            [
              74.40295793116093,
              32.901399355962155
            ],
            [
              74.40299078822136,
              32.90123946379037
            ],
            [
              74.40313495695591,
              32.901219758749235
            ],
            [
              74.40318055450916,
              32.90121469173793
            ],
            [
              74.40345212817192,
              32.90112517449066
            ],
            [
              74.40371498465538,
              32.90112461148882
            ],
            [
              74.40390609204769,
              32.90103115313355
            ],
            [
              74.40401539206505,
              32.90101651506896
            ],
            [
              74.40415553748608,
              32.901063244266645
            ],
            [
              74.40428227186203,
              32.901150509569824
            ],
            [
              74.40439894795418,
              32.90129857888752
            ],
            [
              74.40454244613646,
              32.90147536094257
            ],
            [
              74.40454244613646,
              32.90169943450526
            ],
            [
              74.40466046333313,
              32.901815412056244
            ],
            [
              74.40477713942528,
              32.90192744847823
            ],
            [
              74.40502792596817,
              32.90196742123773
            ],
            [
              74.40510369837284,
              32.90195447231762
            ],
            [
              74.4052753597498,
              32.90191956652355
            ],
            [
              74.40533839166163,
              32.901905491602676
            ],
            [
              74.40556235611439,
              32.901928011474986
            ],
            [
              74.4056984782219,
              32.901939834405646
            ],
            [
              74.40588355064392,
              32.901926322484755
            ],
            [
              74.40602369606493,
              32.901867770803754
            ],
            [
              74.40605454146862,
              32.90182892399405
            ],
            [
              74.40607264637947,
              32.90177262423958
            ],
            [
              74.40607734024525,
              32.9017405333635
            ],
            [
              74.4060867279768,
              32.90171182046455
            ],
            [
              74.40615311264992,
              32.90162399271579
            ],
            [
              74.40628454089165,
              32.90159696877557
            ],
            [
              74.4064112752676,
              32.901612169742975
            ],
            [
              74.40651722252369,
              32.9016256817118
            ],
            [
              74.40663121640682,
              32.90161498473663
            ],
            [
              74.4067271053791,
              32.90157726381398
            ],
            [
              74.4068183004856,
              32.90144552195803
            ],
            [
              74.40694034099577,
              32.90126761384155
            ],
            [
              74.40705500543118,
              32.90121806974549
            ],
            [
              74.40729305148125,
              32.901212439732824
            ],
            [
              74.40736681222916,
              32.901148820564785
            ],
            [
              74.4074184447527,
              32.90107900832779
            ],
            [
              74.40753981471062,
              32.90091798957135
            ],
            [
              74.40770879387856,
              32.90085774821306
            ],
            [
              74.40787576138972,
              32.90092699762139
            ],
            [
              74.40822914242743,
              32.90087970534839
            ],
            [
              74.40846383571625,
              32.900747962454794
            ],
            [
              74.40870456397533,
              32.90061284133469
            ],
            [
              74.40899826586246,
              32.9004484436939
            ],
            [
              74.40903916954994,
              32.90042536043907
            ],
            [
              74.4092108309269,
              32.90035723665197
            ],
            [
              74.40931744873524,
              32.900309381067714
            ],
            [
              74.40938115119934,
              32.90028291973355
            ],
            [
              74.40942741930483,
              32.90027222259623
            ],
            [
              74.40950453281403,
              32.900254206362
            ],
            [
              74.40957829356192,
              32.900235627116636
            ],
            [
              74.40966412425041,
              32.90021479583689
            ],
            [
              74.40977677702904,
              32.900186645451065
            ],
            [
              74.40995648503304,
              32.900141604815154
            ],
            [
              74.41010534763336,
              32.900105572289895
            ],
            [
              74.41017374396324,
              32.90008530398802
            ],
            [
              74.41032730042934,
              32.90004870843121
            ],
            [
              74.4103903323412,
              32.90003407020423
            ],
            [
              74.41043257713318,
              32.90002224701915
            ],
            [
              74.41045604646206,
              32.900017179939354
            ],
            [
              74.41056869924068,
              32.89997213921723
            ],
            [
              74.41068805754185,
              32.899929350510014
            ],
            [
              74.41073432564735,
              32.89990964517739
            ],
            [
              74.41083893179893,
              32.89987023449892
            ],
            [
              74.41091805696487,
              32.89983983196358
            ],
            [
              74.41105552017689,
              32.89978803502744
            ],
            [
              74.41113866865635,
              32.89975650644282
            ],
            [
              74.41117219626904,
              32.89974412021005
            ],
            [
              74.4112506508827,
              32.899713154620606
            ],
            [
              74.41130429506302,
              32.899693449239834
            ],
            [
              74.41139079630375,
              32.899660231588086
            ],
            [
              74.41172875463963,
              32.899497521215594
            ],
            [
              74.41208146512508,
              32.89933086945158
            ],
            [
              74.41212840378284,
              32.899309474945646
            ],
            [
              74.41237650811672,
              32.89908933643969
            ],
            [
              74.41263131797312,
              32.8988686343704
            ],
            [
              74.41275604069233,
              32.89876222424763
            ],
            [
              74.41289082169533,
              32.898689595042796
            ],
            [
              74.41316239535809,
              32.898541521363214
            ],
            [
              74.4132851064205,
              32.89853251307053
            ],
            [
              74.41343329846859,
              32.898521815721786
            ],
            [
              74.41352382302284,
              32.89850098403895
            ],
            [
              74.41371560096741,
              32.89845369047051
            ],
            [
              74.41383562982082,
              32.898421598391856
            ],
            [
              74.4139040261507,
              32.89832138094851
            ],
            [
              74.41400930285452,
              32.89816486134388
            ],
            [
              74.4141186028719,
              32.89800102218086
            ],
            [
              74.4141212850809,
              32.89799539196367
            ],
            [
              74.4142460078001,
              32.89787884638778
            ],
            [
              74.41441096365452,
              32.8977307713528
            ],
            [
              74.41453367471694,
              32.89771388064867
            ],
            [
              74.41490046679974,
              32.89766602363613
            ],
            [
              74.41518411040306,
              32.89736480537545
            ],
            [
              74.41546641290188,
              32.89707146847729
            ],
            [
              74.41564209759235,
              32.896887358258034
            ],
            [
              74.41579833626747,
              32.896679600395125
            ],
            [
              74.41606119275093,
              32.896334462271945
            ],
            [
              74.41624827682972,
              32.896130081313814
            ],
            [
              74.41638238728046,
              32.895986507631484
            ],
            [
              74.4164615124464,
              32.89590148938049
            ],
            [
              74.4165962934494,
              32.8957551001478
            ],
            [
              74.41686116158961,
              32.89552932243389
            ],
            [
              74.41721320152281,
              32.89521852523798
            ],
            [
              74.41747069358826,
              32.894786109934024
            ],
            [
              74.41783547401428,
              32.894326666360755
            ],
            [
              74.41741704940796,
              32.89388523793794
            ],
            [
              74.417062997818,
              32.89342578969234
            ],
            [
              74.41707372665405,
              32.89317354258343
            ],
            [
              74.41727757453918,
              32.89241679694734
            ],
            [
              74.41770672798157,
              32.89020958525364
            ],
            [
              74.41880106925964,
              32.8878851967625
            ],
            [
              74.41979885101318,
              32.886065284143456
            ],
            [
              74.42028164863586,
              32.885596785736574
            ],
            [
              74.42023873329163,
              32.88549767998696
            ],
            [
              74.42012071609497,
              32.88537154523621
            ],
            [
              74.41989541053772,
              32.88512828485278
            ],
            [
              74.41960573196411,
              32.88488502380156
            ],
            [
              74.41918730735777,
              32.88440750942576
            ],
            [
              74.41901564598083,
              32.88412820737179
            ],
            [
              74.4189727306366,
              32.88383088486316
            ],
            [
              74.4189727306366,
              32.88333534513211
            ],
            [
              74.41897541284561,
              32.88308081682948
            ],
            [
              74.41899955272675,
              32.88283755015791
            ],
            [
              74.41902905702591,
              32.882528960919316
            ],
            [
              74.41901296377182,
              32.882204603189116
            ],
            [
              74.41894322633743,
              32.881835194328275
            ],
            [
              74.41887617111206,
              32.88149957152834
            ],
            [
              74.41881716251373,
              32.88085309986879
            ],
            [
              74.41875547170639,
              32.88025167426519
            ],
            [
              74.41862672567368,
              32.87955788984802
            ],
            [
              74.41857308149338,
              32.8793303814379
            ],
            [
              74.41850066184998,
              32.879145671210104
            ],
            [
              74.41822707653046,
              32.87868614653435
            ],
            [
              74.41788375377655,
              32.87822661947628
            ],
            [
              74.41754847764969,
              32.87777835304089
            ],
            [
              74.41724270582199,
              32.87737063134959
            ],
            [
              74.41682696342468,
              32.87681198200919
            ],
            [
              74.41616177558899,
              32.87573071521973
            ],
            [
              74.41541075706482,
              32.874433177663356
            ],
            [
              74.41496014595032,
              32.87354110957688
            ],
            [
              74.41473484039305,
              32.87291260167149
            ],
            [
              74.41450417041779,
              32.872380957097384
            ],
            [
              74.41434323787689,
              32.87189436435401
            ],
            [
              74.4141286611557,
              32.87122529497138
            ],
            [
              74.41404551267624,
              32.870961720798014
            ],
            [
              74.41395431756973,
              32.870238577375524
            ],
            [
              74.41393353044987,
              32.87005441140276
            ],
            [
              74.41390335559845,
              32.86978689134196
            ],
            [
              74.41387318074703,
              32.86953570335016
            ],
            [
              74.4138215482235,
              32.86911104759317
            ],
            [
              74.41385373473167,
              32.86883958223731
            ],
            [
              74.4138852506876,
              32.868571495302604
            ],
            [
              74.41391877830027,
              32.86827412061173
            ],
            [
              74.41395699977875,
              32.86795815890996
            ],
            [
              74.41398650407791,
              32.86771034502277
            ],
            [
              74.41400863230228,
              32.867514909491454
            ],
            [
              74.41405154764652,
              32.86734650792449
            ],
            [
              74.41412329673767,
              32.86705363487237
            ],
            [
              74.41416956484318,
              32.866860450771995
            ],
            [
              74.41423125565052,
              32.86660080617243
            ],
            [
              74.41428422927856,
              32.86639185085585
            ],
            [
              74.41434659063816,
              32.86613276810847
            ],
            [
              74.41446460783482,
              32.865878190410704
            ],
            [
              74.41456384956835,
              32.865665290801424
            ],
            [
              74.41476233303547,
              32.86523442098066
            ],
            [
              74.41484615206718,
              32.86505193430788
            ],
            [
              74.41495209932327,
              32.864819319578736
            ],
            [
              74.41505737602711,
              32.8645900836434
            ],
            [
              74.41517472267151,
              32.86431916768319
            ],
            [
              74.41527932882308,
              32.86406683772847
            ],
            [
              74.41541343927383,
              32.86375705666844
            ],
            [
              74.4155341386795,
              32.863477689548226
            ],
            [
              74.41563740372658,
              32.86323380583877
            ],
            [
              74.4157225638628,
              32.863034980978945
            ],
            [
              74.4158586859703,
              32.862795038769896
            ],
            [
              74.41605851054192,
              32.86244469944905
            ],
            [
              74.41619396209717,
              32.862204755643084
            ],
            [
              74.41638574004173,
              32.861872438032236
            ],
            [
              74.41650442779064,
              32.86166347157489
            ],
            [
              74.41668212413788,
              32.86134692306564
            ],
            [
              74.41677801311016,
              32.861180762808814
            ],
            [
              74.41685579717159,
              32.861043328327305
            ],
            [
              74.41690944135189,
              32.860965598895106
            ],
            [
              74.41706635057926,
              32.8607459283924
            ],
            [
              74.41720582544804,
              32.86054991425375
            ],
            [
              74.41732317209244,
              32.86038037293962
            ],
            [
              74.41742174327374,
              32.86024350047953
            ],
            [
              74.41760949790478,
              32.859977077348624
            ],
            [
              74.41790655255318,
              32.859554065617395
            ],
            [
              74.41793203353882,
              32.85951970638684
            ],
            [
              74.41798835992813,
              32.859401420409476
            ],
            [
              74.41812179982662,
              32.85914006416682
            ],
            [
              74.41831827163696,
              32.8587474650879
            ],
            [
              74.41845171153544,
              32.85848329055469
            ],
            [
              74.4186045974493,
              32.85817292671846
            ],
            [
              74.41869713366032,
              32.857992678620036
            ],
            [
              74.4188104569912,
              32.85764795311173
            ],
            [
              74.4189043343067,
              32.857381522185115
            ],
            [
              74.41897809505463,
              32.85715564671359
            ],
            [
              74.4190666079521,
              32.8568942838542
            ],
            [
              74.4191812723875,
              32.856552933787796
            ],
            [
              74.42018508911133,
              32.85147083076529
            ],
            [
              74.41949844360352,
              32.84123138501963
            ],
            [
              74.42087173461914,
              32.837481433320534
            ],
            [
              74.42996978759766,
              32.83156772610805
            ],
            [
              74.43683624267578,
              32.824932366251716
            ],
            [
              74.4382095336914,
              32.81844077366436
            ],
            [
              74.43735122680664,
              32.812237253094096
            ],
            [
              74.44198608398438,
              32.80906319137108
            ],
            [
              74.44335937499999,
              32.80661042966843
            ],
            [
              74.44541931152344,
              32.80386902766576
            ],
            [
              74.44679260253906,
              32.80242615054725
            ],
            [
              74.44644927978516,
              32.79954032605238
            ],
            [
              74.44747924804688,
              32.79578861416773
            ],
            [
              74.44868087768555,
              32.79391269886276
            ],
            [
              74.4517707824707,
              32.79203674398424
            ],
            [
              74.45297241210938,
              32.791603825700186
            ],
            [
              74.46001052856445,
              32.78814040356287
            ],
            [
              74.46069717407227,
              32.7842438924523
            ],
            [
              74.46258544921875,
              32.780491535254356
            ],
            [
              74.46413040161133,
              32.77572870013365
            ],
            [
              74.46910858154297,
              32.7761616956792
            ],
            [
              74.4737434387207,
              32.77717201042541
            ],
            [
              74.47614669799805,
              32.77572870013365
            ],
            [
              74.47734832763672,
              32.77399669688296
            ],
            [
              74.47992324829102,
              32.772264659923465
            ],
            [
              74.48301315307617,
              32.770532589256035
            ],
            [
              74.48421478271484,
              32.76836745352148
            ],
            [
              74.48507308959961,
              32.76490312680306
            ],
            [
              74.49125289916992,
              32.765480523951865
            ],
            [
              74.49588775634766,
              32.76562487265395
            ],
            [
              74.49777603149414,
              32.76605791735576
            ],
            [
              74.50035095214844,
              32.76605791735576
            ],
            [
              74.50275421142578,
              32.76562487265395
            ],
            [
              74.50309753417969,
              32.76461442682433
            ],
            [
              74.50447082519531,
              32.76562487265395
            ],
            [
              74.50567245483398,
              32.76620226512159
            ],
            [
              74.50790405273438,
              32.76634661265338
            ],
            [
              74.50876235961914,
              32.76562487265395
            ],
            [
              74.511079788208,
              32.764361813574936
            ],
            [
              74.50940608978271,
              32.76306264839869
            ],
            [
              74.51155185699463,
              32.76078906372296
            ],
            [
              74.51146602630615,
              32.759525936039076
            ],
            [
              74.51395511627197,
              32.75948984641337
            ],
            [
              74.51519966125488,
              32.75649435649161
            ],
            [
              74.51378345489502,
              32.7550507109093
            ],
            [
              74.51464176177979,
              32.75414842053654
            ],
            [
              74.5133113861084,
              32.75212725693016
            ],
            [
              74.51271057128906,
              32.75173023726077
            ],
            [
              74.5109510421753,
              32.7510083787826
            ],
            [
              74.51099395751953,
              32.75158586603317
            ],
            [
              74.50966358184814,
              32.75158586603317
            ],
            [
              74.50979232788085,
              32.750647447349735
            ],
            [
              74.51052188873291,
              32.74960073792395
            ],
            [
              74.51013565063477,
              32.74801260358348
            ],
            [
              74.5098352432251,
              32.747254620394244
            ],
            [
              74.51125144958496,
              32.74584692021809
            ],
            [
              74.51223850250244,
              32.74516110951031
            ],
            [
              74.5142126083374,
              32.74418652731786
            ],
            [
              74.5164442062378,
              32.74516110951031
            ],
            [
              74.51867580413818,
              32.74822916902439
            ],
            [
              74.52069282531738,
              32.74783213198053
            ],
            [
              74.52335357666016,
              32.74851792212663
            ],
            [
              74.5248556137085,
              32.74840963982297
            ],
            [
              74.5262289047241,
              32.74808479212226
            ],
            [
              74.52700138092041,
              32.74750728217391
            ],
            [
              74.5283317565918,
              32.74671319988194
            ],
            [
              74.53022003173828,
              32.745485967872085
            ],
            [
              74.53219413757324,
              32.74512501406368
            ],
            [
              74.53378200531004,
              32.74544987255705
            ],
            [
              74.53468322753906,
              32.745738634667845
            ],
            [
              74.5358419418335,
              32.74642444092992
            ],
            [
              74.53678607940674,
              32.746785389473686
            ],
            [
              74.53777313232422,
              32.74815698060257
            ],
            [
              74.53691482543945,
              32.74891495611393
            ],
            [
              74.53661441802979,
              32.75003386055739
            ],
            [
              74.53747272491455,
              32.75003386055739
            ],
            [
              74.53824520111084,
              32.74981729950392
            ],
            [
              74.53884601593018,
              32.749564644276084
            ],
            [
              74.54120635986328,
              32.74963683155715
            ],
            [
              74.54146385192871,
              32.75003386055739
            ],
            [
              74.54185009002686,
              32.75010604745824
            ],
            [
              74.5420217514038,
              32.75122493694032
            ],
            [
              74.54309463500977,
              32.75140540166956
            ],
            [
              74.54283714294434,
              32.75071963375332
            ],
            [
              74.54532623291016,
              32.74859011025593
            ],
            [
              74.5448112487793,
              32.747254620394244
            ],
            [
              74.54451084136963,
              32.746460535850105
            ],
            [
              74.54408168792725,
              32.74544987255705
            ],
            [
              74.54399585723877,
              32.74512501406368
            ],
            [
              74.54476833343506,
              32.7450889186024
            ],
            [
              74.54545497894287,
              32.74552206317249
            ],
            [
              74.54678535461426,
              32.745630348985976
            ],
            [
              74.5473861694336,
              32.745883015372264
            ],
            [
              74.54811573028564,
              32.74711024191268
            ],
            [
              74.5482873916626,
              32.7483735456925
            ],
            [
              74.54815864562988,
              32.74996167359807
            ],
            [
              74.54841613769531,
              32.75061135412601
            ],
            [
              74.5491886138916,
              32.75180242278683
            ],
            [
              74.54996109008789,
              32.75259645971237
            ],
            [
              74.55172061920166,
              32.75357094990069
            ],
            [
              74.55365180969238,
              32.756169538276
            ],
            [
              74.55399513244629,
              32.75689135492404
            ],
            [
              74.55472469329834,
              32.757540984905035
            ],
            [
              74.5555830001831,
              32.75862369100871
            ],
            [
              74.55699920654297,
              32.75782970781984
            ],
            [
              74.56008911132811,
              32.758371060761974
            ],
            [
              74.56232070922852,
              32.75934548776435
            ],
            [
              74.56549644470215,
              32.76024772548112
            ],
            [
              74.56717014312744,
              32.76057252882118
            ],
            [
              74.56875801086426,
              32.760536439619685
            ],
            [
              74.5697021484375,
              32.760283814799635
            ],
            [
              74.57201957702637,
              32.7580823396024
            ],
            [
              74.57360744476318,
              32.7576492561078
            ],
            [
              74.57442283630371,
              32.75739662309657
            ],
            [
              74.57515239715576,
              32.75671090131051
            ],
            [
              74.57583904266357,
              32.75631390207365
            ],
            [
              74.57605361938477,
              32.75541162449883
            ],
            [
              74.57583904266357,
              32.75270473692648
            ],
            [
              74.57515239715576,
              32.75151368033159
            ],
            [
              74.57601070404053,
              32.750791820098385
            ],
            [
              74.5766544342041,
              32.75118884395061
            ],
            [
              74.57789897918701,
              32.75075572693316
            ],
            [
              74.57794189453125,
              32.75035870115045
            ],
            [
              74.57961559295654,
              32.749853393049385
            ],
            [
              74.58098888397217,
              32.75191070096623
            ],
            [
              74.58197593688965,
              32.75346267373962
            ],
            [
              74.58364963531494,
              32.753967961365056
            ],
            [
              74.58682537078857,
              32.752307719831215
            ],
            [
              74.58879947662354,
              32.75086400638496
            ],
            [
              74.59098815917967,
              32.7518746082544
            ],
            [
              74.59167480468749,
              32.75342658165667
            ],
            [
              74.59321975708008,
              32.7560251742443
            ],
            [
              74.59433555603027,
              32.75653044733134
            ],
            [
              74.59888458251952,
              32.756963536267065
            ],
            [
              74.60540771484375,
              32.75782970781984
            ],
            [
              74.6075963973999,
              32.758371060761974
            ],
            [
              74.61068630218506,
              32.75811842979854
            ],
            [
              74.61270332336424,
              32.75826279043684
            ],
            [
              74.61291790008545,
              32.759742473486014
            ],
            [
              74.61391568183899,
              32.76015750212084
            ],
            [
              74.61503148078918,
              32.76061764030247
            ],
            [
              74.61629748344421,
              32.76117702077177
            ],
            [
              74.61750984191895,
              32.76161008710865
            ],
            [
              74.61920499801636,
              32.761312354228316
            ],
            [
              74.62138295173645,
              32.76069884091121
            ],
            [
              74.6230673789978,
              32.75924624105739
            ],
            [
              74.62391495704651,
              32.758019181723945
            ],
            [
              74.62482690811157,
              32.75736053260789
            ],
            [
              74.62446212768555,
              32.75672894668835
            ],
            [
              74.62707996368408,
              32.75588080997857
            ],
            [
              74.62785243988037,
              32.755592080745096
            ],
            [
              74.62969779968262,
              32.75431985641081
            ],
            [
              74.632648229599,
              32.75225358099928
            ],
            [
              74.63522315025328,
              32.75163098206692
            ],
            [
              74.63554501533507,
              32.752343812367535
            ],
            [
              74.6372938156128,
              32.75176633003113
            ],
            [
              74.63789463043213,
              32.75473491031865
            ],
            [
              74.63851690292358,
              32.75588080997857
            ],
            [
              74.63877439498901,
              32.75729737421752
            ],
            [
              74.63770151138304,
              32.75755903011463
            ],
            [
              74.63770151138304,
              32.75947180159506
            ],
            [
              74.63651061058044,
              32.75988683149145
            ],
            [
              74.6352767944336,
              32.76078004144591
            ],
            [
              74.63422536849976,
              32.761998040580075
            ],
            [
              74.63374257087708,
              32.76251230187846
            ],
            [
              74.63351726531982,
              32.76283709695755
            ],
            [
              74.63257312774658,
              32.76346863955278
            ],
            [
              74.6316397190094,
              32.76463247060044
            ],
            [
              74.63145732879637,
              32.765976721634644
            ],
            [
              74.63074922561646,
              32.76655411182022
            ],
            [
              74.63022351264954,
              32.767149541526734
            ],
            [
              74.63010549545288,
              32.76832234596698
            ],
            [
              74.63021278381348,
              32.769287642643825
            ],
            [
              74.63000893592834,
              32.76988305406566
            ],
            [
              74.6311891078949,
              32.77066790849078
            ],
            [
              74.63137149810791,
              32.77082127004142
            ],
            [
              74.63137149810791,
              32.77167828560701
            ],
            [
              74.63201522827148,
              32.772733756595045
            ],
            [
              74.63239073753357,
              32.7746822855338
            ],
            [
              74.63135004043579,
              32.775205494371775
            ],
            [
              74.6318006515503,
              32.776278964943536
            ],
            [
              74.63200449943542,
              32.77664881314959
            ],
            [
              74.63431119918823,
              32.778389785274996
            ],
            [
              74.63581323623657,
              32.77941811550221
            ],
            [
              74.63727235794067,
              32.780617819079666
            ],
            [
              74.63778734207153,
              32.7809696087908
            ],
            [
              74.63822722434998,
              32.781240215314355
            ],
            [
              74.63935375213622,
              32.782566175382364
            ],
            [
              74.63942885398865,
              32.78258421551915
            ],
            [
              74.64075922966003,
              32.782403813986825
            ],
            [
              74.64139223098755,
              32.782187331665185
            ],
            [
              74.64214324951172,
              32.78204300982477
            ],
            [
              74.64282989501953,
              32.78206105006763
            ],
            [
              74.64324831962585,
              32.78204300982477
            ],
            [
              74.64372038841248,
              32.78196182868664
            ],
            [
              74.64437484741211,
              32.7817543654416
            ],
            [
              74.64494347572327,
              32.7815920025645
            ],
            [
              74.64538335800171,
              32.781483760481855
            ],
            [
              74.64589834213257,
              32.781348457693326
            ],
            [
              74.64617729187012,
              32.78125825571999
            ],
            [
              74.64898824691772,
              32.78120413449209
            ],
            [
              74.64933156967163,
              32.78167318404007
            ],
            [
              74.64965343475342,
              32.78164612355645
            ],
            [
              74.65100526809692,
              32.78114099301795
            ],
            [
              74.65141296386719,
              32.78161906306461
            ],
            [
              74.65238928794861,
              32.781438659575194
            ],
            [
              74.65365529060362,
              32.780942548093165
            ],
            [
              74.65430974960327,
              32.78299011762934
            ],
            [
              74.65559720993042,
              32.784505469144335
            ],
            [
              74.65806484222412,
              32.78667923189846
            ],
            [
              74.6582579612732,
              32.78712119376113
            ],
            [
              74.65707778930664,
              32.78738276199238
            ],
            [
              74.65606927871704,
              32.78832981294711
            ],
            [
              74.65547919273376,
              32.788852941532056
            ],
            [
              74.6547281742096,
              32.78930391198061
            ],
            [
              74.65217471122742,
              32.790864252089726
            ],
            [
              74.65053319931029,
              32.79182930423609
            ],
            [
              74.6498680114746,
              32.79203674398424
            ],
            [
              74.6492350101471,
              32.79239750761111
            ],
            [
              74.64684247970581,
              32.79369624455026
            ],
            [
              74.6467137336731,
              32.79376839604629
            ],
            [
              74.6451473236084,
              32.7938856421025
            ],
            [
              74.64259386062622,
              32.79575253924663
            ],
            [
              74.63937520980835,
              32.79814247113704
            ],
            [
              74.63880658149719,
              32.799639527824084
            ],
            [
              74.63872075080872,
              32.800126516734274
            ],
            [
              74.63837742805481,
              32.80045117452578
            ],
            [
              74.63790535926819,
              32.800929140783516
            ],
            [
              74.63766932487488,
              32.80138004999181
            ],
            [
              74.63682174682617,
              32.80272374586997
            ],
            [
              74.63622093200684,
              32.80339107721427
            ],
            [
              74.6352446079254,
              32.80442813625328
            ],
            [
              74.6345579624176,
              32.80554634287819
            ],
            [
              74.63431119918823,
              32.80604231711967
            ],
            [
              74.63357090950012,
              32.80696211656941
            ],
            [
              74.63291645050049,
              32.80777369641453
            ],
            [
              74.63253021240234,
              32.809135330396465
            ],
            [
              74.63381767272949,
              32.810478909042786
            ],
            [
              74.6350085735321,
              32.812264304269306
            ],
            [
              74.6364676952362,
              32.814383287406166
            ],
            [
              74.63743329048157,
              32.81517676595996
            ],
            [
              74.63773369789124,
              32.81542021818661
            ],
            [
              74.63821649551392,
              32.816195654166165
            ],
            [
              74.63887095451355,
              32.81697108337824
            ],
            [
              74.63957905769348,
              32.81792683565381
            ],
            [
              74.63987946510315,
              32.81830552710771
            ],
            [
              74.64015841484068,
              32.81875634816254
            ],
            [
              74.64046955108643,
              32.81904487243705
            ],
            [
              74.64116692543028,
              32.8196850323252
            ],
            [
              74.64173555374146,
              32.81997355358365
            ],
            [
              74.64256167411804,
              32.82043338240254
            ],
            [
              74.64287281036377,
              32.820631739197445
            ],
            [
              74.64536190032959,
              32.82301198618965
            ],
            [
              74.6467137336731,
              32.824238149142985
            ],
            [
              74.64759349822998,
              32.82554543658928
            ],
            [
              74.64848399162292,
              32.826023267888544
            ],
            [
              74.64849472045898,
              32.8262035809183
            ],
            [
              74.64884877204895,
              32.82634783107856
            ],
            [
              74.65005040168762,
              32.82706006281056
            ],
            [
              74.6503722667694,
              32.82744773084648
            ],
            [
              74.65065121650696,
              32.82766410296791
            ],
            [
              74.65102672576904,
              32.8278804745622
            ],
            [
              74.65142369270325,
              32.82817798464364
            ],
            [
              74.65302228927612,
              32.829638474224076
            ],
            [
              74.65508222579956,
              32.8302695425372
            ],
            [
              74.65610146522522,
              32.83049492299077
            ],
            [
              74.65822577476501,
              32.83057605981403
            ],
            [
              74.65895533561707,
              32.83044083173409
            ],
            [
              74.6612298488617,
              32.82949422940855
            ],
            [
              74.6612298488617,
              32.828367308721965
            ],
            [
              74.66179847717285,
              32.82701498502215
            ],
            [
              74.66315031051636,
              32.825815907451776
            ],
            [
              74.66632604598999,
              32.82520283898109
            ],
            [
              74.66816067695618,
              32.8265912526927
            ],
            [
              74.67116475105286,
              32.82887217095775
            ],
            [
              74.67231273651123,
              32.830206435907684
            ],
            [
              74.67217326164246,
              32.83084651535614
            ],
            [
              74.67245221138,
              32.83135136349752
            ],
            [
              74.67282772064209,
              32.83163083177016
            ],
            [
              74.67347145080566,
              32.83220779574422
            ],
            [
              74.67498421669006,
              32.83301013003913
            ],
            [
              74.67703342437744,
              32.834632806454486
            ],
            [
              74.67943668365479,
              32.83589486760844
            ],
            [
              74.68230128288269,
              32.83737325928629
            ],
            [
              74.68524098396301,
              32.837878070318396
            ],
            [
              74.68628168106079,
              32.83832879202854
            ],
            [
              74.68820214271545,
              32.83923924290312
            ],
            [
              74.6884274482727,
              32.84025785509128
            ],
            [
              74.68980073928833,
              32.84035701140565
            ],
            [
              74.69021916389465,
              32.84085279131621
            ],
            [
              74.69123840332031,
              32.84123138501963
            ],
            [
              74.69228982925414,
              32.84167307563279
            ],
            [
              74.69285845756531,
              32.84187138498908
            ],
            [
              74.69370603561401,
              32.841952511416224
            ],
            [
              74.69610929489136,
              32.84234912843718
            ],
            [
              74.69839453697205,
              32.84261954811717
            ],
            [
              74.70035791397095,
              32.84286292512477
            ],
            [
              74.70394134521484,
              32.842898980921
            ],
            [
              74.70621585845947,
              32.842835883268
            ],
            [
              74.70680594444275,
              32.840897862079856
            ],
            [
              74.7065269947052,
              32.83847302249249
            ],
            [
              74.70634460449219,
              32.83691351817029
            ],
            [
              74.70623731613159,
              32.836616037356045
            ],
            [
              74.7059154510498,
              32.83629151169454
            ],
            [
              74.70578670501709,
              32.835552309926214
            ],
            [
              74.7050142288208,
              32.835462162948076
            ],
            [
              74.70497131347656,
              32.83494832342482
            ],
            [
              74.70496058464049,
              32.834605762090575
            ],
            [
              74.70507860183716,
              32.834371377258236
            ],
            [
              74.7051751613617,
              32.834136991807185
            ],
            [
              74.70560431480406,
              32.834290243902885
            ],
            [
              74.70609784126282,
              32.8344344809278
            ],
            [
              74.70620512962341,
              32.83449758455253
            ],
            [
              74.7061836719513,
              32.83479507246499
            ],
            [
              74.70653772354126,
              32.83478605769441
            ],
            [
              74.70681667327881,
              32.834641821240616
            ],
            [
              74.70703125,
              32.8342271401308
            ],
            [
              74.70710635185242,
              32.833749352972596
            ],
            [
              74.70682740211487,
              32.83297407022641
            ],
            [
              74.70680594444275,
              32.83142348442626
            ],
            [
              74.70695614814758,
              32.82968355068087
            ],
            [
              74.70688104629517,
              32.82700596946172
            ],
            [
              74.70715999603271,
              32.825716734897846
            ],
            [
              74.70669865608215,
              32.82368818108816
            ],
            [
              74.70660209655762,
              32.82223660970399
            ],
            [
              74.70620512962341,
              32.821335000628736
            ],
            [
              74.70650553703308,
              32.820072732549804
            ],
            [
              74.70639824867249,
              32.81942355912533
            ],
            [
              74.70632314682007,
              32.818846512098986
            ],
            [
              74.70660209655762,
              32.81771043981257
            ],
            [
              74.70640897750854,
              32.81731371273473
            ],
            [
              74.70624804496764,
              32.816844851176974
            ],
            [
              74.70523953437805,
              32.81496036342075
            ],
            [
              74.70365166664124,
              32.814067697375464
            ],
            [
              74.70331907272339,
              32.8138693259253
            ],
            [
              74.70266461372375,
              32.81335536147167
            ],
            [
              74.70221400260925,
              32.812913530003726
            ],
            [
              74.7020959854126,
              32.81276024102197
            ],
            [
              74.70181703567503,
              32.81266105389285
            ],
            [
              74.70157027244568,
              32.81249874744277
            ],
            [
              74.69329833984375,
              32.667124733120325
            ],
            [
              74.75372314453125,
              32.47732919639942
            ],
            [
              75.05035400390625,
              32.48659682936049
            ],
            [
              75.32501220703125,
              32.35212281198644
            ],
            [
              75.333251953125,
              32.33355894864106
            ],
            [
              75.52001953125,
              32.287132632616384
            ],
            [
              75.68756103515625,
              32.39619671866136
            ],
            [
              75.92926025390625,
              32.64168769084188
            ],
            [
              75.87158203125,
              32.83575063295596
            ],
            [
              75.8221435546875,
              32.88420028540548
            ],
            [
              75.87982177734375,
              32.93953889877841
            ],
            [
              76.13250732421875,
              33.0063602132054
            ],
            [
              76.3055419921875,
              33.063924198120645
            ],
            [
              76.5802001953125,
              33.201924189778936
            ],
            [
              76.783447265625,
              33.215712251730736
            ],
            [
              76.7889404296875,
              33.25476662931654
            ],
            [
              76.59393310546875,
              33.49101671911273
            ],
            [
              76.4373779296875,
              33.58259116393916
            ],
            [
              76.33026123046874,
              33.64663552343716
            ],
            [
              76.30279541015625,
              33.64663552343716
            ],
            [
              76.190185546875,
              33.594031146632354
            ],
            [
              76.22314453125,
              33.669496972795535
            ],
            [
              76.2451171875,
              33.79512630103207
            ],
            [
              76.05560302734375,
              33.95247360616282
            ],
            [
              76.0528564453125,
              34.01396527491264
            ],
            [
              75.97320556640625,
              34.00713506435885
            ],
            [
              75.87158203125,
              33.99119576995599
            ],
            [
              75.80291748046875,
              34.00030430441023
            ],
            [
              75.80017089843749,
              34.043556504127444
            ],
            [
              75.70953369140625,
              34.093610452768715
            ],
            [
              75.67108154296875,
              34.17999758688084
            ],
            [
              75.67108154296875,
              34.24586516842103
            ],
            [
              75.59967041015625,
              34.25721644329402
            ],
            [
              75.51727294921875,
              34.264026473152875
            ],
            [
              75.465087890625,
              34.32302363048832
            ],
            [
              75.377197265625,
              34.334364487026306
            ],
            [
              75.3387451171875,
              34.39331222316112
            ],
            [
              75.35247802734375,
              34.44542371620849
            ],
            [
              75.3057861328125,
              34.48165602990584
            ],
            [
              75.3387451171875,
              34.52466147177172
            ],
            [
              75.34149169921875,
              34.55633549113736
            ],
            [
              75.26458740234375,
              34.621907605630376
            ],
            [
              75.11077880859375,
              34.646766246519114
            ],
            [
              74.9102783203125,
              34.68065238482746
            ],
            [
              74.72625732421875,
              34.68291096793206
            ],
            [
              74.608154296875,
              34.743869417874286
            ],
            [
              74.53948974609375,
              34.77771580360469
            ],
            [
              74.410400390625,
              34.784483415461345
            ],
            [
              74.29504394531249,
              34.77094763658632
            ],
            [
              74.18243408203125,
              34.703235443285095
            ],
            [
              74.12200927734375,
              34.655803905058974
            ],
            [
              73.970947265625,
              34.68065238482746
            ],
            [
              73.9215087890625,
              34.6241677899049
            ],
            [
              73.97369384765625,
              34.58121376394335
            ],
            [
              73.88580322265625,
              34.49523909266902
            ],
            [
              73.85009765625,
              34.43409789359469
            ],
            [
              73.7567138671875,
              34.36837785748377
            ],
            [
              73.84735107421875,
              34.347971491244955
            ],
            [
              73.93524169921875,
              34.352506668675936
            ],
            [
              73.93524169921875,
              34.30714385628804
            ],
            [
              73.9764404296875,
              34.275375297643876
            ],
            [
              74.0093994140625,
              34.23905366851639
            ],
            [
              74.00115966796875,
              34.1890858311724
            ],
            [
              73.927001953125,
              34.120900139826965
            ],
            [
              73.90228271484375,
              34.07996230865873
            ],
            [
              73.90228271484375,
              34.03672867489511
            ],
            [
              73.9764404296875,
              34.016241889667015
            ],
            [
              74.02313232421875,
              34.02990029603907
            ],
            [
              74.08905029296875,
              34.043556504127444
            ],
            [
              74.168701171875,
              34.025347738147936
            ],
            [
              74.23187255859375,
              34.016241889667015
            ],
            [
              74.267578125,
              33.96614226559745
            ],
            [
              74.27581787109375,
              33.90005673964575
            ],
            [
              74.23187255859375,
              33.85673152928873
            ],
            [
              74.15496826171874,
              33.813384329112786
            ],
            [
              74.036865234375,
              33.78371305547283
            ],
            [
              74.00390625,
              33.75174787568194
            ],
            [
              73.95172119140624,
              33.701492795584365
            ],
            [
              74.036865234375,
              33.59174327144985
            ],
            [
              74.124755859375,
              33.55512901742288
            ],
            [
              74.168701171875,
              33.49330726228523
            ],
            [
              74.18792724609375,
              33.39705230475205
            ],
            [
              74.16046142578125,
              33.33741240611175
            ],
            [
              74.05059814453125,
              33.28232392051035
            ],
            [
              74.0093994140625,
              33.247875947924385
            ],
            [
              74.0972900390625,
              33.16284622181141
            ],
            [
              74.16046142578125,
              33.1329513125159
            ],
            [
              74.16595458984375,
              33.07773395720986
            ],
            [
              74.2236328125,
              33.06162236089505
            ],
            [
              74.24835205078124,
              33.04550781490999
            ],
            [
              74.28955078125,
              33.038600678138195
            ],
            [
              74.33624267578125,
              33.03399561940715
            ],
            [
              74.33074951171875,
              33.00175347002964
            ],
            [
              74.3280029296875,
              32.93953889877841
            ],
            [
              74.3115234375,
              32.91879097277371
            ],
            [
              74.32714462280273,
              32.92052015245145
            ],
            [
              74.34087753295898,
              32.91979966502504
            ],
            [
              74.35186386108398,
              32.92167292013293
            ],
            [
              74.36147689819335,
              32.91936736975363
            ],
            [
              74.37108993530273,
              32.919511468412054
            ],
            [
              74.37383651733398,
              32.91821457203976
            ],
            [
              74.37325716018677,
              32.91730493199488
            ],
            [
              74.37411546707153,
              32.91708877853027
            ],
            [
              74.37630414962769,
              32.91603502283085
            ],
            [
              74.3770444393158,
              32.91613409441379
            ],
            [
              74.37773108482361,
              32.91622415939298
            ],
            [
              74.37787860631943,
              32.91607555212818
            ]
          ]
        ]
      }
    }
  ]
}